datasig/__init__.py
datasig/algo.py
datasig/benchmark/__init__.py
datasig/benchmark/accuracy.py
datasig/benchmark/benchmark.py
datasig/benchmark/logger.py
datasig/benchmark/plot.py
datasig/benchmark/utils.py
datasig/dataset.py
datasig/fingerprint.py
datasig/py.typed
datasig/test/__init__.py
datasig/test/test_arff.py
datasig/test/test_csv.py
datasig/test/test_torch_mnist.py
datasig/test/utils.py
datasig/utils.py
datasig-0.0.4.dist-info/licenses/LICENSE
datasig-0.0.4.dist-info/WHEEL
datasig-0.0.4.dist-info/METADATA
datasig-0.0.4.dist-info/RECORD
