Metadata-Version: 2.4
Name: datasig
Version: 0.0.4
Summary: Dataset fingerprinting library
Author: Lucas Bourtoule, Boyan Milanov
Author-email: Lucas Bourtoule <lucas.bourtoule@trailofbits.com>, Boyan Milanov <boyan.milanov@trailofbits.com>
License-Expression: AGPL-3.0-only
License-File: LICENSE
Requires-Dist: datasketch>=1.6.5
Requires-Dist: numpy>=1.24.4
Requires-Dist: pillow>=10.4.0
Requires-Dist: torch>=2.5.1
Requires-Python: >=3.8
